MANIFEST.in
README.rst
pytest_rage.py
setup.py
pytest_rage.egg-info/PKG-INFO
pytest_rage.egg-info/SOURCES.txt
pytest_rage.egg-info/dependency_links.txt
pytest_rage.egg-info/entry_points.txt
pytest_rage.egg-info/requires.txt
pytest_rage.egg-info/top_level.txt