Metadata-Version: 1.0
Name: pytest-rage
Version: 0.1
Summary: pytest plugin to implement PEP712
Home-page: http://github.com/santagada/pytest-rage/
Author: Leonardo Santagada
Author-email: santagada@gmail.com
License: MIT
Platform: UNKNOWN
Classifier: Development Status :: 3 - Alpha
Classifier: Topic :: Software Development :: Testing
Classifier: Intended Audience :: Developers
Classifier: Operating System :: OS Independent
